rda_python_metrics/PgIPInfo.py
rda_python_metrics/PgView.py
rda_python_metrics/__init__.py
rda_python_metrics/fill_awsusage.py
rda_python_metrics/fill_cdgusage.py
rda_python_metrics/fill_codusage.py
rda_python_metrics/fill_country.py
rda_python_metrics/fill_endtime.py
rda_python_metrics/fill_globususage.py
rda_python_metrics/fill_ipinfo.py
rda_python_metrics/fill_oneorder.py
rda_python_metrics/fill_osdfusage.py
rda_python_metrics/fill_rdadb.py
rda_python_metrics/fill_tdsusage.py
rda_python_metrics/fill_user.py
rda_python_metrics/fillawsusage.py
rda_python_metrics/fillawsusage.usg
rda_python_metrics/fillcdgusage.py
rda_python_metrics/fillcdgusage.usg
rda_python_metrics/fillcodusage.py
rda_python_metrics/fillcodusage.usg
rda_python_metrics/fillcountry.py
rda_python_metrics/fillendtime.py
rda_python_metrics/fillgdexusage.py
rda_python_metrics/fillgdexusage.usg
rda_python_metrics/fillglobususage.py
rda_python_metrics/fillglobususage.usg
rda_python_metrics/fillipinfo.py
rda_python_metrics/fillipinfo.usg
rda_python_metrics/filloneorder.py
rda_python_metrics/filloneorder.usg
rda_python_metrics/fillosdfusage.py
rda_python_metrics/fillosdfusage.usg
rda_python_metrics/fillrdadb.py
rda_python_metrics/fillrdadb.usg
rda_python_metrics/filltdsusage.py
rda_python_metrics/filltdsusage.usg
rda_python_metrics/filluser.py
rda_python_metrics/filluser.usg
rda_python_metrics/fillzenodousage.py
rda_python_metrics/log_arch.py
rda_python_metrics/logarch.py
rda_python_metrics/logarch.usg
rda_python_metrics/pg_ipinfo.py
rda_python_metrics/pg_person.py
rda_python_metrics/pg_username.py
rda_python_metrics/pg_view.py
rda_python_metrics/pgperson.py
rda_python_metrics/pgsyspath.py
rda_python_metrics/pgusername.py
rda_python_metrics/view_allusage.py
rda_python_metrics/view_awsusage.py
rda_python_metrics/view_checkusage.py
rda_python_metrics/view_codusage.py
rda_python_metrics/view_ordusage.py
rda_python_metrics/view_osdfusage.py
rda_python_metrics/view_rqstusage.py
rda_python_metrics-2.0.0.dist-info/licenses/LICENSE
rda_python_metrics-2.0.0.dist-info/METADATA
rda_python_metrics-2.0.0.dist-info/WHEEL
rda_python_metrics-2.0.0.dist-info/entry_points.txt
rda_python_metrics-2.0.0.dist-info/top_level.txt
rda_python_metrics-2.0.0.dist-info/RECORD
