Metadata-Version: 2.4
Name: rda_python_metrics
Version: 2.0.0
Summary: RDA Python Package to gather and view data usage metrics
Author-email: Zaihua Ji <zji@ucar.edu>
Project-URL: Homepage, https://github.com/NCAR/rda-python-metrics
Classifier: Programming Language :: Python :: 3
Classifier: License :: OSI Approved :: MIT License
Classifier: Operating System :: OS Independent
Classifier: Development Status :: 5 - Production/Stable
Requires-Python: >=3.7
License-File: LICENSE
Requires-Dist: rda_python_common
Requires-Dist: rda_python_setuid
Requires-Dist: geoip2
Requires-Dist: ipinfo
Requires-Dist: httplib2
Requires-Dist: dnspython
Requires-Dist: unidecode
Dynamic: license-file
